unique_deep_research/__init__.py
unique_deep_research/config.py
unique_deep_research/markdown_utils.py
unique_deep_research/service.py
unique_deep_research/templates/clarifying_agent.j2
unique_deep_research/templates/openai/oai_research_system_message.j2
unique_deep_research/templates/report_cleanup_prompt.j2
unique_deep_research/templates/research_instructions_agent.j2
unique_deep_research/templates/unique/compress_research_system.j2
unique_deep_research/templates/unique/lead_agent_system.j2
unique_deep_research/templates/unique/report_writer_system_open_deep_research.j2
unique_deep_research/templates/unique/research_agent_system.j2
unique_deep_research/unique_custom/__init__.py
unique_deep_research/unique_custom/agents.py
unique_deep_research/unique_custom/citation.py
unique_deep_research/unique_custom/state.py
unique_deep_research/unique_custom/tools.py
unique_deep_research/unique_custom/utils.py
unique_deep_research-3.1.0.dist-info/LICENSE
unique_deep_research-3.1.0.dist-info/METADATA
unique_deep_research-3.1.0.dist-info/WHEEL
unique_deep_research-3.1.0.dist-info/RECORD
