Metadata-Version: 2.1
Name: unique_deep_research
Version: 3.1.0
Summary: Deep Research Tool for complex research tasks
License: Proprietary
Author: Martin Fadler
Author-email: martin.fadler@unique.ch
Requires-Python: >=3.12,<4.0
Classifier: License :: Other/Proprietary License
Classifier: Programming Language :: Python :: 3
Classifier: Programming Language :: Python :: 3.12
Requires-Dist: beautifulsoup4 (>=4.12.0,<5.0.0)
Requires-Dist: fake-useragent (>=2.0.0,<3.0.0)
Requires-Dist: httpx (>=0.28.0,<0.29.0)
Requires-Dist: jinja2 (>=3.1.2,<4.0.0)
Requires-Dist: langchain-core (>=1.0.0,<2.0.0)
Requires-Dist: langchain[openai] (>=1.1.0,<2.0.0)
Requires-Dist: langgraph (>=1.0.0,<2.0.0)
Requires-Dist: markdownify (>=0.14.0,<0.15.0)
Requires-Dist: openai (>=1.99.0,<2.0.0)
Requires-Dist: pydantic (>=2.8.2,<3.0.0)
Requires-Dist: tiktoken (>=0.12.0,<0.13.0)
Requires-Dist: timeout-decorator (>=0.5.0,<0.6.0)
Requires-Dist: typing-extensions (>=4.9.0,<5.0.0)
Requires-Dist: unique-web-search (>=1.7.0,<2.0.0)
Requires-Dist: unique_toolkit (>=1.38.3,<2.0.0)
